setup.py
My_Client_Student.egg-info/PKG-INFO
My_Client_Student.egg-info/SOURCES.txt
My_Client_Student.egg-info/dependency_links.txt
My_Client_Student.egg-info/requires.txt
My_Client_Student.egg-info/top_level.txt
client/__init__.py
client/client.py
client/client/__init__.py
client/client/add_contact.py
client/client/database.py
client/client/del_contact.py
client/client/main_window.py
client/client/main_window_conv.py
client/client/start_dialog.py
client/client/transport.py
client/logs/__init__.py
client/logs/config_client_log.py
client/logs/config_server_log.py
client/system/__init__.py
client/system/config.py
client/system/decos.py
client/system/descryptors.py
client/system/errors.py
client/system/metaclasses.py
client/system/utils.py
client/unit_tests/__init__.py
client/unit_tests/test_client.py
client/unit_tests/test_utils.py